task_multiprocess/__init__.py
task_multiprocess/main.py
task_multiprocess-0.0.6.dist-info/LICENSE
task_multiprocess-0.0.6.dist-info/METADATA
task_multiprocess-0.0.6.dist-info/WHEEL
task_multiprocess-0.0.6.dist-info/top_level.txt
task_multiprocess-0.0.6.dist-info/RECORD
