Metadata-Version: 2.1
Name: task-multiprocess
Version: 0.0.6
Summary: run tasks in parallel
Home-page: 
Author: raymond
Author-email: lei20190123@gmail.com
Classifier: Programming Language :: Python :: 3
Classifier: License :: OSI Approved :: MIT License
Classifier: Operating System :: OS Independent
License-File: LICENSE
